Embed_Builder/__init__.py
Embed_Builder/exemplo.py
embed_builder.pt_br-0.0.1.dist-info/LICENSE
embed_builder.pt_br-0.0.1.dist-info/METADATA
embed_builder.pt_br-0.0.1.dist-info/WHEEL
embed_builder.pt_br-0.0.1.dist-info/top_level.txt
embed_builder.pt_br-0.0.1.dist-info/RECORD
