Metadata-Version: 2.1
Name: embed-builder.pt-br
Version: 0.0.1
Author: Leticia Sousa
Author-email: leticialimasousa2007@gmail.com
License: MIT License
License-File: LICENSE
Requires-Dist: discord.py
